refmod/__init__.py
refmod/config.py
refmod/dtm_helper.py
refmod/hapke/__init__.py
refmod/hapke/inverse.py
refmod/hapke/mimsa.py
refmod/hapke/models.py
refmod/hapke/functions/__init__.py
refmod/hapke/functions/h.py
refmod/hapke/functions/legendre.py
refmod/hapke/functions/opposition_effect.py
refmod/hapke/functions/phase.py
refmod/hapke/functions/roughness.py
refmod/hapke/functions/vectors.py
refmod-0.2.0.dist-info/licenses/LICENSE
refmod-0.2.0.dist-info/METADATA
refmod-0.2.0.dist-info/WHEEL
refmod-0.2.0.dist-info/top_level.txt
refmod-0.2.0.dist-info/RECORD
