Metadata-Version: 2.4
Name: refmod
Version: 0.2.0
Summary: Reflectance models in python
Author-email: Mirza Arnaut <mirza.arnaut@tu-dortmund.de>
License: MIT
Requires-Python: >=3.10
License-File: LICENSE
Requires-Dist: numpy>=2.1
Requires-Dist: numba>=0.61.0
Requires-Dist: pydantic>=2.11.5
Requires-Dist: scipy>=1.15.3
Dynamic: license-file
